syslog_parse
