Metadata-Version: 2.1
Name: syslog-parse
Version: 0.2.1.1909161139
Summary: syslog parser
Home-page: https://github.com/BingerYang/syslog_parse
Author: binger
Author-email: <xuehen_521@126.com>
Maintainer: binger
Maintainer-email: <xuehen_521@126.com>
License: 2009-2018 (c) binger <xuehen_521@126.com>
